setup.py
BrokenLeaf_STT/__init__.py
BrokenLeaf_STT.egg-info/PKG-INFO
BrokenLeaf_STT.egg-info/SOURCES.txt
BrokenLeaf_STT.egg-info/dependency_links.txt
BrokenLeaf_STT.egg-info/top_level.txt