Metadata-Version: 2.1
Name: BrokenLeaf-STT
Version: 0.1
Summary: This is a very well developed Speech-to-Text program created by me, Broken Leaf....
Author: Broken Leaf
Author-email: brokenleaf2010@gmail.com
